Metadata-Version: 1.1
Name: indian-word2number
Version: 1.2
Summary: Convert number words eg. three hundred and forty two to numbers (342) for indian currency standards.
Home-page: https://github.com/credavenue/ca-ds-nlp-Indian-word2number
Author: Darshan Patel
Author-email: darshan.patel@go-yubi.com
License: MIT
Keywords: numbers,convert,words,indian,currency
Platform: UNKNOWN
Classifier: Intended Audience :: Developers
Classifier: Programming Language :: Python
